yacce/__init__.py
yacce/__main__.py
yacce/common.py
yacce/mod_bazel.py
yacce/mod_from_log.py
yacce-0.9.8.dist-info/licenses/LICENSE
yacce-0.9.8.dist-info/METADATA
yacce-0.9.8.dist-info/WHEEL
yacce-0.9.8.dist-info/entry_points.txt
yacce-0.9.8.dist-info/top_level.txt
yacce-0.9.8.dist-info/RECORD
