Metadata-Version: 2.4
Name: yacce
Version: 0.9.8
Summary: Non-intrusive bazel compile_commands.json extractor
Author-email: Aleksei Rechinskii <5dpea9nhd@mozmail.com>
License-Expression: MIT
Project-URL: Homepage, https://github.com/Arech/yacce
Project-URL: Source, https://github.com/Arech/yacce
Project-URL: Bugtracker, https://github.com/Arech/yacce/issues
Keywords: bazel,compile_commands.json,extractor
Classifier: Programming Language :: Python
Classifier: Programming Language :: Python :: 3
Classifier: Programming Language :: Python :: 3.10
Classifier: Programming Language :: Python :: 3.11
Classifier: Programming Language :: Python :: 3.12
Classifier: Programming Language :: Python :: 3.13
Classifier: Programming Language :: Python :: 3.14
Classifier: Development Status :: 4 - Beta
Classifier: Intended Audience :: Developers
Classifier: Intended Audience :: Information Technology
Classifier: Operating System :: POSIX :: Linux
Classifier: Topic :: Scientific/Engineering
Classifier: Topic :: Scientific/Engineering :: Information Analysis
Classifier: Topic :: Software Development
Classifier: Topic :: Utilities
Requires-Python: >=3.10
License-File: LICENSE
Requires-Dist: rich
Dynamic: license-file
